mpesa_sdk/__init__.py
mpesa_sdk/gateway.py
mpesa_sdk/urls.py
mpesa_sdk/helpers/__init__.py
mpesa_sdk/helpers/utils.py
tests/__init__.py
tests/base.py
tests/test_generate_token.py
tests/test_stk_push.py
mpesa_sdk-1.0.7.dist-info/LICENSE
mpesa_sdk-1.0.7.dist-info/METADATA
mpesa_sdk-1.0.7.dist-info/WHEEL
mpesa_sdk-1.0.7.dist-info/top_level.txt
mpesa_sdk-1.0.7.dist-info/RECORD
